repman/__init__.py
repman/_repmanclass.py
repman/_repmanfunctions.py
repman/_repmanhelps.py
repman/repman.py
RepMan-1.0.5.dist-info/LICENSE
RepMan-1.0.5.dist-info/METADATA
RepMan-1.0.5.dist-info/WHEEL
RepMan-1.0.5.dist-info/entry_points.txt
RepMan-1.0.5.dist-info/top_level.txt
RepMan-1.0.5.dist-info/RECORD
