Metadata-Version: 2.1
Name: RepMan
Version: 1.0.5
Summary: RepMan: Repository Manager (alias: Project Manager)
Author-email: Soumyo Deep Gupta <deep.main.ac@gmail.com>
Maintainer-email: Soumyo Deep Gupta <deep.main.ac@gmail.com>
License: MIT License
Project-URL: GitHub, https://github.com/d33pster/RepMan
Project-URL: Issues, https://github.com/d33pster/RepMan/issues
Project-URL: Homepage, https://d33pster.github.io/RepMan/
Keywords: d33pster,repman,RepMan,Repo Man,Repository Manager
Classifier: Development Status :: 4 - Beta
Classifier: Intended Audience :: Developers
Classifier: Topic :: Software Development
Classifier: License :: OSI Approved :: MIT License
Classifier: Operating System :: OS Independent
Requires-Python: >=3.12
License-File: LICENSE
Requires-Dist: optioner >=1.4.5
Requires-Dist: termcolor
Requires-Dist: gdown
Requires-Dist: tk
Requires-Dist: pandas
Requires-Dist: tabulate
Requires-Dist: requests
